dbus_client_gen/__init__.py
dbus_client_gen/_errors.py
dbus_client_gen/_managed_objects.py
dbus_client_gen/_managed_objects_queries.py
dbus_client_gen/_version.py
dbus_client_gen-0.5.1.dist-info/LICENSE
dbus_client_gen-0.5.1.dist-info/METADATA
dbus_client_gen-0.5.1.dist-info/WHEEL
dbus_client_gen-0.5.1.dist-info/top_level.txt
dbus_client_gen-0.5.1.dist-info/RECORD
