Metadata-Version: 2.1
Name: dbus-client-gen
Version: 0.5.1
Summary: generates classes and methods useful to a D-Bus client
Home-page: https://github.com/mulkieran/dbus-client-gen
Author: Anne Mulhern
Author-email: amulhern@redhat.com
License: MPL-2.0
Platform: Linux
Classifier: Development Status :: 4 - Beta
Classifier: Intended Audience :: Developers
Classifier: License :: OSI Approved :: Mozilla Public License 2.0 (MPL 2.0)
Classifier: Operating System :: POSIX :: Linux
Classifier: Programming Language :: Python
Classifier: Programming Language :: Python :: 3
Classifier: Programming Language :: Python :: Implementation :: CPython
Classifier: Topic :: Software Development :: Libraries
Classifier: Topic :: Software Development :: Libraries :: Python Modules
License-File: LICENSE
